nosop_py/__init__.py
tests/__init__.py
tests/test_NosoNodeInfo.py
tests/test_NosoPoolInfo.py
tests/test_NosoPoolPublic.py
nosop_py-0.4.9.dist-info/LICENSE
nosop_py-0.4.9.dist-info/METADATA
nosop_py-0.4.9.dist-info/WHEEL
nosop_py-0.4.9.dist-info/top_level.txt
nosop_py-0.4.9.dist-info/RECORD
