Metadata-Version: 2.1
Name: nosop-py
Version: 0.4.9
Summary: Set of classes and tools to communicate with a Noso wallet using NosoP
Home-page: https://github.com/Friends-Of-Noso/NosoP-Py
Author: Gustavo 'Gus' Carreno
Author-email: guscarreno@gmail.com
License: MIT
License-File: LICENSE
